MANIFEST.in
setup.py
account/__init__.py
account/facebook.py
account/models.py
account/tests.py
account/urls.py
account/views.py
account/templates/base.html
account/templates/account/header.html
account/templates/account/home.html
account/templates/account/login-form.html
django_carrots.egg-info/PKG-INFO
django_carrots.egg-info/SOURCES.txt
django_carrots.egg-info/dependency_links.txt
django_carrots.egg-info/requires.txt
django_carrots.egg-info/top_level.txt