Metadata-Version: 1.0
Name: django-carrots
Version: 1.10
Summary: Basic account application for Django Workshops by Geek Girl Carrots
Home-page: http://geekgirlscarrots.pl/
Author: Krzysztof Płocharz
Author-email: krzysztof@plocharz.info
License: PSF
Keywords: django facebook account
Platform: UNKNOWN
